yaconfiglib/__init__.py
yaconfiglib/loader.py
yaconfiglib/backends/__init__.py
yaconfiglib/backends/base.py
yaconfiglib/backends/ini.py
yaconfiglib/backends/jinja2.py
yaconfiglib/backends/json.py
yaconfiglib/backends/toml.py
yaconfiglib/backends/yaml.py
yaconfiglib/utils/__init__.py
yaconfiglib/utils/enum.py
yaconfiglib/utils/jinja2.py
yaconfiglib/utils/log.py
yaconfiglib/utils/merge.py
yaconfiglib/utils/source.py
yaconfiglib-0.3.5.dist-info/METADATA
yaconfiglib-0.3.5.dist-info/WHEEL
yaconfiglib-0.3.5.dist-info/licenses/LICENSE
yaconfiglib-0.3.5.dist-info/RECORD
